aepybamm/__init__.py
aepybamm/bpx_tools.py
aepybamm/func.py
aepybamm/params.py
aepybamm/plot.py
aepybamm/pybamm_print_tools.py
aepybamm/pybamm_tools.py
aepybamm/sci_tools.py
aepybamm/simulate.py
aepybamm-0.2.1.dist-info/METADATA
aepybamm-0.2.1.dist-info/WHEEL
aepybamm-0.2.1.dist-info/licenses/LICENSE
aepybamm-0.2.1.dist-info/RECORD
