Metadata-Version: 2.4
Name: aepybamm
Version: 0.2.1
Summary: Interfacing between About:Energy's BPX electrochemical parameter sets for batteries and the PyBaMM package for battery modelling.
Project-URL: Homepage, https://github.com/About-Energy-OpenSource/AEPyBaMM
Project-URL: Issues, https://github.com/About-Energy-OpenSource/AEPyBaMM/issues
Project-URL: Changelog, https://github.com/About-Energy-OpenSource/AEPyBaMM/blob/main/CHANGELOG.md
Project-URL: Documentation, https://github.com/About-Energy-OpenSource/AEPyBaMM/blob/main/README.md
Author-email: "About:Energy Limited" <edmund@aboutenergy.co.uk>
License-Expression: BSD-3-Clause
License-File: LICENSE
Classifier: Operating System :: OS Independent
Classifier: Programming Language :: Python :: 3
Requires-Python: >=3.10
Requires-Dist: bpx<0.6,>=0.5
Requires-Dist: matplotlib
Requires-Dist: numpy
Requires-Dist: packaging
Requires-Dist: pandas[output-formatting]
Requires-Dist: pybamm[bpx]>=25.10
